plutus/__init__.py
plutus/backtest.py
plutus/benchmark.py
plutus/calculations.py
plutus/plots.py
plutus/trade_breaker.py
plutus_backtest-0.3.0.1.dist-info/LICENSE
plutus_backtest-0.3.0.1.dist-info/METADATA
plutus_backtest-0.3.0.1.dist-info/WHEEL
plutus_backtest-0.3.0.1.dist-info/top_level.txt
plutus_backtest-0.3.0.1.dist-info/RECORD
